{"symbol":"USD/JPY","price":161.865,"timeframes":{"1m":{"touch":{"price":161.876,"dist":1.2,"touches":1,"rank":1,"conf":3,"side":"R"},"r2":null,"r1":{"price":162.089,"dist":22.4,"touches":52,"rank":3,"conf":6},"s1":{"price":161.819,"dist":4.5,"touches":1,"rank":1,"conf":3},"s2":{"price":161.768,"dist":9.7,"touches":2,"rank":2,"conf":3}},"5m":{"touch":null,"r2":null,"r1":{"price":162.139,"dist":27.4,"touches":60,"rank":3,"conf":6},"s1":null,"s2":null},"15m":{"touch":{"price":161.85,"dist":1.5,"touches":1,"rank":1,"conf":3,"side":"S"},"r2":null,"r1":{"price":162.198,"dist":33.4,"touches":14,"rank":3,"conf":6},"s1":{"price":161.757,"dist":10.7,"touches":1,"rank":1,"conf":3},"s2":{"price":161.494,"dist":37.1,"touches":1,"rank":1,"conf":3}},"1h":{"touch":null,"r2":{"price":162.429,"dist":56.4,"touches":1,"rank":1,"conf":2},"r1":{"price":162.024,"dist":15.9,"touches":1,"rank":1,"conf":6},"s1":{"price":161.428,"dist":43.7,"touches":15,"rank":3,"conf":3},"s2":{"price":160.963,"dist":90.2,"touches":2,"rank":1,"conf":3}},"4h":{"touch":null,"r2":{"price":162.368,"dist":50.3,"touches":2,"rank":2,"conf":2},"r1":{"price":162.03,"dist":16.5,"touches":3,"rank":1,"conf":6},"s1":{"price":161.587,"dist":27.8,"touches":12,"rank":3,"conf":3},"s2":{"price":161.079,"dist":78.6,"touches":2,"rank":1,"conf":3}},"1d":{"touch":null,"r2":{"price":162.845,"dist":98,"touches":1,"rank":1,"conf":2},"r1":{"price":162.007,"dist":14.3,"touches":1,"rank":1,"conf":6},"s1":{"price":161.813,"dist":5.2,"touches":1,"rank":1,"conf":3},"s2":{"price":161.001,"dist":86.4,"touches":1,"rank":1,"conf":3}}},"confluence":[{"price":162.081,"dist":21.6,"side":"R","tfs":["1m","5m","15m","1h","4h","1d"],"count":6},{"price":161.814,"dist":5.1,"side":"S","tfs":["1m","15m","1d"],"count":3},{"price":161.466,"dist":39.9,"side":"S","tfs":["15m","1h","4h"],"count":3},{"price":161.014,"dist":85,"side":"S","tfs":["1h","4h","1d"],"count":3},{"price":160.651,"dist":121.4,"side":"S","tfs":["1h","4h","1d"],"count":3},{"price":162.398,"dist":53.4,"side":"R","tfs":["1h","4h"],"count":2}],"updated":"2026-07-07T02:10:35.916Z"}