{"symbol":"USD/JPY","price":162.434,"timeframes":{"1m":{"touch":{"price":162.41,"dist":2.4,"touches":61,"rank":3,"conf":5,"side":"S"},"r2":null,"r1":null,"s1":null,"s2":null},"5m":{"touch":{"price":162.413,"dist":2.1,"touches":72,"rank":3,"conf":5,"side":"S"},"r2":null,"r1":null,"s1":{"price":162.168,"dist":26.7,"touches":2,"rank":1,"conf":2},"s2":null},"15m":{"touch":{"price":162.407,"dist":2.8,"touches":25,"rank":3,"conf":5,"side":"S"},"r2":null,"r1":null,"s1":{"price":162.166,"dist":26.8,"touches":1,"rank":1,"conf":2},"s2":null},"1h":{"touch":null,"r2":null,"r1":null,"s1":{"price":162.361,"dist":7.3,"touches":16,"rank":3,"conf":5},"s2":{"price":161.974,"dist":46.1,"touches":4,"rank":2,"conf":2}},"4h":{"touch":null,"r2":null,"r1":{"price":162.779,"dist":34.5,"touches":2,"rank":1,"conf":2},"s1":{"price":162.357,"dist":7.7,"touches":10,"rank":3,"conf":5},"s2":{"price":161.668,"dist":76.6,"touches":8,"rank":3,"conf":2}},"1d":{"touch":null,"r2":null,"r1":{"price":162.779,"dist":34.5,"touches":2,"rank":2,"conf":2},"s1":{"price":162.007,"dist":42.7,"touches":1,"rank":1,"conf":2},"s2":{"price":161.813,"dist":62.1,"touches":1,"rank":1,"conf":1}}},"confluence":[{"price":162.39,"dist":4.5,"side":"S","tfs":["1m","5m","15m","1h","4h"],"count":5},{"price":162.167,"dist":26.7,"side":"S","tfs":["5m","15m"],"count":2},{"price":162.779,"dist":34.5,"side":"R","tfs":["4h","1d"],"count":2},{"price":161.99,"dist":44.4,"side":"S","tfs":["1h","1d"],"count":2},{"price":161.655,"dist":78,"side":"S","tfs":["1h","4h"],"count":2},{"price":161.302,"dist":113.2,"side":"S","tfs":["4h","1d"],"count":2}],"updated":"2026-07-18T05:05:15.147Z"}