{"symbol":"USD/JPY","price":161.738,"timeframes":{"1m":{"touch":{"price":161.718,"dist":2.1,"touches":58,"rank":3,"conf":6,"side":"S"},"r2":null,"r1":{"price":161.825,"dist":8.7,"touches":1,"rank":1,"conf":6},"s1":{"price":161.624,"dist":11.5,"touches":1,"rank":1,"conf":6},"s2":null},"5m":{"touch":{"price":161.729,"dist":0.9,"touches":59,"rank":3,"conf":6,"side":"S"},"r2":null,"r1":null,"s1":{"price":161.492,"dist":24.6,"touches":2,"rank":1,"conf":1},"s2":{"price":161.365,"dist":37.4,"touches":5,"rank":1,"conf":4}},"15m":{"touch":{"price":161.714,"dist":2.5,"touches":20,"rank":3,"conf":6,"side":"S"},"r2":null,"r1":{"price":162.426,"dist":68.8,"touches":1,"rank":1,"conf":3},"s1":{"price":161.319,"dist":41.9,"touches":3,"rank":1,"conf":4},"s2":null},"1h":{"touch":null,"r2":{"price":162.236,"dist":49.8,"touches":3,"rank":2,"conf":3},"r1":{"price":161.892,"dist":15.4,"touches":9,"rank":3,"conf":6},"s1":{"price":161.307,"dist":43.1,"touches":2,"rank":2,"conf":4},"s2":null},"4h":{"touch":null,"r2":{"price":162.329,"dist":59.1,"touches":3,"rank":2,"conf":3},"r1":{"price":162.03,"dist":29.2,"touches":3,"rank":1,"conf":6},"s1":{"price":161.658,"dist":8,"touches":9,"rank":3,"conf":6},"s2":{"price":161.322,"dist":41.7,"touches":1,"rank":1,"conf":4}},"1d":{"touch":null,"r2":{"price":162.007,"dist":26.9,"touches":1,"rank":1,"conf":6},"r1":{"price":161.813,"dist":7.5,"touches":1,"rank":1,"conf":6},"s1":{"price":161.001,"dist":73.7,"touches":1,"rank":1,"conf":2},"s2":{"price":160.626,"dist":111.2,"touches":3,"rank":2,"conf":2}}},"confluence":[{"price":161.801,"dist":6.3,"side":"R","tfs":["1m","5m","15m","1h","4h","1d"],"count":6},{"price":161.328,"dist":41,"side":"S","tfs":["5m","15m","1h","4h"],"count":4},{"price":162.357,"dist":61.9,"side":"R","tfs":["15m","1h","4h"],"count":3},{"price":162.747,"dist":100.9,"side":"R","tfs":["1h","4h","1d"],"count":3},{"price":161.04,"dist":69.8,"side":"S","tfs":["4h","1d"],"count":2},{"price":160.635,"dist":110.3,"side":"S","tfs":["4h","1d"],"count":2}],"updated":"2026-07-11T03:20:37.657Z"}