{"symbol":"USD/JPY","price":163.363,"timeframes":{"1m":{"touch":{"price":163.387,"dist":2.5,"touches":11,"rank":3,"conf":5,"side":"R"},"r2":null,"r1":null,"s1":{"price":163.263,"dist":9.9,"touches":1,"rank":1,"conf":5},"s2":{"price":163.091,"dist":27.2,"touches":46,"rank":3,"conf":4}},"5m":{"touch":null,"r2":null,"r1":{"price":163.418,"dist":5.5,"touches":1,"rank":1,"conf":5},"s1":{"price":163.09,"dist":27.3,"touches":53,"rank":3,"conf":4},"s2":null},"15m":{"touch":null,"r2":null,"r1":null,"s1":{"price":163.313,"dist":5,"touches":1,"rank":1,"conf":5},"s2":{"price":163.098,"dist":26.4,"touches":24,"rank":3,"conf":4}},"1h":{"touch":null,"r2":null,"r1":null,"s1":{"price":163.23,"dist":13.2,"touches":4,"rank":3,"conf":5},"s2":{"price":163.022,"dist":34.1,"touches":2,"rank":2,"conf":4}},"4h":{"touch":null,"r2":null,"r1":null,"s1":{"price":163.313,"dist":5,"touches":1,"rank":1,"conf":5},"s2":{"price":162.487,"dist":87.5,"touches":13,"rank":3,"conf":2}},"1d":{"touch":null,"r2":null,"r1":null,"s1":{"price":162.779,"dist":58.4,"touches":2,"rank":2,"conf":3},"s2":{"price":162.007,"dist":135.5,"touches":1,"rank":1,"conf":1}}},"confluence":[{"price":163.321,"dist":4.2,"side":"S","tfs":["1m","5m","15m","1h","4h"],"count":5},{"price":163.075,"dist":28.8,"side":"S","tfs":["1m","5m","15m","1h"],"count":4},{"price":162.802,"dist":56,"side":"S","tfs":["15m","1h","1d"],"count":3},{"price":162.457,"dist":90.5,"side":"S","tfs":["1h","4h"],"count":2},{"price":161.302,"dist":206.1,"side":"S","tfs":["4h","1d"],"count":2},{"price":160.635,"dist":272.8,"side":"S","tfs":["4h","1d"],"count":2}],"updated":"2026-07-23T08:55:19.647Z"}