{"symbol":"USD/JPY","price":163.796,"timeframes":{"1m":{"touch":null,"r2":null,"r1":{"price":163.84,"dist":4.4,"touches":1,"rank":1,"conf":3},"s1":{"price":163.752,"dist":4.4,"touches":1,"rank":1,"conf":3},"s2":{"price":163.695,"dist":10.1,"touches":1,"rank":1,"conf":3}},"5m":{"touch":null,"r2":null,"r1":null,"s1":{"price":163.752,"dist":4.4,"touches":1,"rank":1,"conf":3},"s2":{"price":163.661,"dist":13.5,"touches":1,"rank":1,"conf":3}},"15m":{"touch":null,"r2":null,"r1":null,"s1":{"price":163.599,"dist":19.7,"touches":1,"rank":1,"conf":3},"s2":{"price":163.435,"dist":36.1,"touches":1,"rank":1,"conf":5}},"1h":{"touch":null,"r2":null,"r1":null,"s1":{"price":163.23,"dist":56.6,"touches":4,"rank":3,"conf":5},"s2":{"price":163.022,"dist":77.5,"touches":2,"rank":2,"conf":3}},"4h":{"touch":null,"r2":null,"r1":null,"s1":{"price":163.313,"dist":48.4,"touches":1,"rank":1,"conf":5},"s2":{"price":162.487,"dist":130.9,"touches":13,"rank":3,"conf":2}},"1d":{"touch":null,"r2":null,"r1":null,"s1":{"price":162.779,"dist":101.8,"touches":2,"rank":2,"conf":2},"s2":{"price":162.007,"dist":178.9,"touches":1,"rank":1,"conf":1}}},"confluence":[{"price":163.335,"dist":46.1,"side":"S","tfs":["1m","5m","15m","1h","4h"],"count":5},{"price":163.685,"dist":11.2,"side":"S","tfs":["1m","5m","15m"],"count":3},{"price":163.07,"dist":72.7,"side":"S","tfs":["5m","15m","1h"],"count":3},{"price":162.785,"dist":101.1,"side":"S","tfs":["1h","1d"],"count":2},{"price":162.457,"dist":134,"side":"S","tfs":["1h","4h"],"count":2},{"price":161.788,"dist":200.9,"side":"S","tfs":["4h","1d"],"count":2}],"updated":"2026-07-23T13:25:22.095Z"}