{"symbol":"USD/JPY","price":162.342,"timeframes":{"1m":{"touch":{"price":162.314,"dist":2.8,"touches":8,"rank":3,"conf":6,"side":"S"},"r2":null,"r1":{"price":162.595,"dist":25.3,"touches":11,"rank":1,"conf":5},"s1":{"price":162.256,"dist":8.6,"touches":2,"rank":2,"conf":6},"s2":{"price":162.141,"dist":20.2,"touches":31,"rank":3,"conf":6}},"5m":{"touch":null,"r2":{"price":162.62,"dist":27.8,"touches":8,"rank":3,"conf":5},"r1":{"price":162.5,"dist":15.8,"touches":1,"rank":1,"conf":5},"s1":{"price":162.223,"dist":11.9,"touches":34,"rank":3,"conf":6},"s2":{"price":161.941,"dist":40.1,"touches":7,"rank":1,"conf":6}},"15m":{"touch":null,"r2":null,"r1":{"price":162.637,"dist":29.5,"touches":2,"rank":2,"conf":5},"s1":{"price":161.897,"dist":44.5,"touches":68,"rank":3,"conf":6},"s2":{"price":161.563,"dist":77.9,"touches":1,"rank":1,"conf":3}},"1h":{"touch":null,"r2":null,"r1":{"price":162.673,"dist":33.1,"touches":1,"rank":1,"conf":5},"s1":{"price":162.281,"dist":6.1,"touches":2,"rank":2,"conf":6},"s2":{"price":161.618,"dist":72.4,"touches":63,"rank":3,"conf":3}},"4h":{"touch":null,"r2":null,"r1":{"price":162.673,"dist":33.1,"touches":1,"rank":1,"conf":5},"s1":{"price":162.03,"dist":31.2,"touches":3,"rank":2,"conf":6},"s2":{"price":161.779,"dist":56.3,"touches":4,"rank":2,"conf":6}},"1d":{"touch":null,"r2":null,"r1":null,"s1":{"price":162.007,"dist":33.5,"touches":1,"rank":1,"conf":6},"s2":{"price":161.813,"dist":52.9,"touches":1,"rank":1,"conf":6}}},"confluence":[{"price":162.04,"dist":30.2,"side":"S","tfs":["1m","5m","15m","1h","4h","1d"],"count":6},{"price":162.616,"dist":27.4,"side":"R","tfs":["1m","5m","15m","1h","4h"],"count":5},{"price":161.543,"dist":79.9,"side":"S","tfs":["15m","1h","4h"],"count":3},{"price":161.027,"dist":131.5,"side":"S","tfs":["4h","1d"],"count":2},{"price":160.756,"dist":158.6,"side":"S","tfs":["4h","1d"],"count":2},{"price":159.518,"dist":282.4,"side":"S","tfs":["4h","1d"],"count":2}],"updated":"2026-07-08T00:00:54.145Z"}