{"symbol":"USD/JPY","price":162.215,"timeframes":{"1m":{"touch":null,"r2":null,"r1":{"price":162.278,"dist":6.3,"touches":1,"rank":1,"conf":6},"s1":{"price":162.098,"dist":11.7,"touches":53,"rank":3,"conf":6},"s2":null},"5m":{"touch":{"price":162.22,"dist":0.6,"touches":57,"rank":3,"conf":6,"side":"R"},"r2":null,"r1":null,"s1":{"price":161.966,"dist":24.9,"touches":1,"rank":1,"conf":6},"s2":{"price":161.898,"dist":31.7,"touches":2,"rank":2,"conf":6}},"15m":{"touch":{"price":162.206,"dist":0.9,"touches":58,"rank":3,"conf":6,"side":"S"},"r2":null,"r1":null,"s1":{"price":161.647,"dist":56.8,"touches":3,"rank":1,"conf":6},"s2":{"price":161.466,"dist":74.9,"touches":1,"rank":1,"conf":2}},"1h":{"touch":null,"r2":null,"r1":{"price":162.335,"dist":12.1,"touches":9,"rank":3,"conf":6},"s1":{"price":161.771,"dist":44.3,"touches":14,"rank":3,"conf":6},"s2":{"price":161.466,"dist":74.9,"touches":1,"rank":1,"conf":2}},"4h":{"touch":null,"r2":{"price":162.779,"dist":56.4,"touches":2,"rank":1,"conf":2},"r1":{"price":162.363,"dist":14.8,"touches":5,"rank":3,"conf":6},"s1":{"price":162.094,"dist":12.1,"touches":1,"rank":1,"conf":6},"s2":{"price":161.668,"dist":54.6,"touches":9,"rank":3,"conf":6}},"1d":{"touch":null,"r2":null,"r1":{"price":162.779,"dist":56.4,"touches":2,"rank":2,"conf":2},"s1":{"price":162.007,"dist":20.7,"touches":1,"rank":1,"conf":6},"s2":{"price":161.813,"dist":40.2,"touches":1,"rank":1,"conf":6}}},"confluence":[{"price":162.026,"dist":18.9,"side":"S","tfs":["1m","5m","15m","1h","4h","1d"],"count":6},{"price":162.779,"dist":56.4,"side":"R","tfs":["4h","1d"],"count":2},{"price":161.466,"dist":74.9,"side":"S","tfs":["15m","1h"],"count":2},{"price":161.302,"dist":91.3,"side":"S","tfs":["4h","1d"],"count":2},{"price":160.635,"dist":157.9,"side":"S","tfs":["4h","1d"],"count":2}],"updated":"2026-07-15T20:30:49.230Z"}