{"symbol":"USD/JPY","price":163.02,"timeframes":{"1m":{"touch":null,"r2":null,"r1":null,"s1":{"price":162.829,"dist":19.1,"touches":58,"rank":3,"conf":6},"s2":{"price":162.667,"dist":35.3,"touches":1,"rank":1,"conf":6}},"5m":{"touch":{"price":163.037,"dist":1.7,"touches":1,"rank":1,"conf":6,"side":"R"},"r2":null,"r1":null,"s1":{"price":162.926,"dist":9.4,"touches":1,"rank":1,"conf":6},"s2":{"price":162.558,"dist":46.2,"touches":50,"rank":3,"conf":6}},"15m":{"touch":{"price":163.037,"dist":1.7,"touches":1,"rank":1,"conf":6,"side":"R"},"r2":null,"r1":null,"s1":{"price":162.518,"dist":50.2,"touches":23,"rank":3,"conf":6},"s2":{"price":162.268,"dist":75.2,"touches":1,"rank":1,"conf":2}},"1h":{"touch":null,"r2":null,"r1":null,"s1":{"price":162.745,"dist":27.5,"touches":1,"rank":1,"conf":6},"s2":{"price":162.422,"dist":59.8,"touches":27,"rank":3,"conf":6}},"4h":{"touch":null,"r2":null,"r1":null,"s1":{"price":162.458,"dist":56.2,"touches":12,"rank":3,"conf":6},"s2":{"price":161.683,"dist":133.6,"touches":7,"rank":3,"conf":1}},"1d":{"touch":null,"r2":null,"r1":null,"s1":{"price":162.779,"dist":24.1,"touches":2,"rank":2,"conf":6},"s2":{"price":162.007,"dist":101.3,"touches":1,"rank":1,"conf":1}}},"confluence":[{"price":162.725,"dist":29.5,"side":"S","tfs":["1m","5m","15m","1h","4h","1d"],"count":6},{"price":162.217,"dist":80.3,"side":"S","tfs":["15m","1h"],"count":2},{"price":161.302,"dist":171.8,"side":"S","tfs":["4h","1d"],"count":2},{"price":160.635,"dist":238.4,"side":"S","tfs":["4h","1d"],"count":2}],"updated":"2026-07-21T15:55:20.169Z"}