{"symbol":"USD/JPY","price":162.993,"timeframes":{"1m":{"touch":{"price":162.998,"dist":0.5,"touches":7,"rank":3,"conf":2,"side":"R"},"r2":null,"r1":null,"s1":{"price":162.774,"dist":21.9,"touches":53,"rank":3,"conf":3},"s2":null},"5m":{"touch":null,"r2":null,"r1":{"price":163.037,"dist":4.4,"touches":1,"rank":1,"conf":2},"s1":{"price":162.558,"dist":43.5,"touches":52,"rank":3,"conf":4},"s2":null},"15m":{"touch":null,"r2":null,"r1":null,"s1":{"price":162.451,"dist":54.2,"touches":75,"rank":3,"conf":4},"s2":null},"1h":{"touch":null,"r2":null,"r1":null,"s1":{"price":162.745,"dist":24.8,"touches":1,"rank":1,"conf":3},"s2":{"price":162.422,"dist":57.1,"touches":27,"rank":3,"conf":4}},"4h":{"touch":null,"r2":null,"r1":null,"s1":{"price":162.458,"dist":53.5,"touches":12,"rank":3,"conf":4},"s2":{"price":161.683,"dist":131,"touches":7,"rank":3,"conf":1}},"1d":{"touch":null,"r2":null,"r1":null,"s1":{"price":162.779,"dist":21.4,"touches":2,"rank":2,"conf":3},"s2":{"price":162.007,"dist":98.6,"touches":1,"rank":1,"conf":1}}},"confluence":[{"price":162.472,"dist":52.1,"side":"S","tfs":["5m","15m","1h","4h"],"count":4},{"price":162.766,"dist":22.7,"side":"S","tfs":["1m","1h","1d"],"count":3},{"price":163.018,"dist":2.4,"side":"R","tfs":["1m","5m"],"count":2},{"price":161.302,"dist":169.1,"side":"S","tfs":["4h","1d"],"count":2},{"price":160.635,"dist":235.8,"side":"S","tfs":["4h","1d"],"count":2}],"updated":"2026-07-21T15:15:27.362Z"}