{"symbol":"USD/JPY","price":163.181,"timeframes":{"1m":{"touch":{"price":163.201,"dist":2,"touches":33,"rank":3,"conf":3,"side":"R"},"r2":null,"r1":null,"s1":{"price":163.005,"dist":17.6,"touches":21,"rank":1,"conf":3},"s2":null},"5m":{"touch":{"price":163.207,"dist":2.6,"touches":7,"rank":3,"conf":3,"side":"R"},"r2":null,"r1":null,"s1":{"price":162.999,"dist":18.2,"touches":7,"rank":3,"conf":3},"s2":{"price":162.571,"dist":61,"touches":37,"rank":3,"conf":4}},"15m":{"touch":{"price":163.204,"dist":2.3,"touches":2,"rank":2,"conf":3,"side":"R"},"r2":null,"r1":null,"s1":{"price":163.012,"dist":16.9,"touches":3,"rank":2,"conf":3},"s2":{"price":162.537,"dist":64.4,"touches":18,"rank":3,"conf":4}},"1h":{"touch":null,"r2":null,"r1":null,"s1":{"price":162.745,"dist":43.6,"touches":1,"rank":1,"conf":2},"s2":{"price":162.426,"dist":75.5,"touches":26,"rank":3,"conf":4}},"4h":{"touch":null,"r2":null,"r1":null,"s1":{"price":162.458,"dist":72.3,"touches":12,"rank":3,"conf":4},"s2":{"price":161.683,"dist":149.8,"touches":7,"rank":3,"conf":1}},"1d":{"touch":null,"r2":null,"r1":null,"s1":{"price":162.779,"dist":40.2,"touches":2,"rank":2,"conf":2},"s2":{"price":162.007,"dist":117.4,"touches":1,"rank":1,"conf":1}}},"confluence":[{"price":162.498,"dist":68.3,"side":"S","tfs":["5m","15m","1h","4h"],"count":4},{"price":163.204,"dist":2.3,"side":"R","tfs":["1m","5m","15m"],"count":3},{"price":163.005,"dist":17.6,"side":"S","tfs":["1m","5m","15m"],"count":3},{"price":162.762,"dist":41.9,"side":"S","tfs":["1h","1d"],"count":2},{"price":161.302,"dist":187.9,"side":"S","tfs":["4h","1d"],"count":2},{"price":160.635,"dist":254.6,"side":"S","tfs":["4h","1d"],"count":2}],"updated":"2026-07-21T21:05:21.442Z"}