{"symbol":"USD/JPY","price":162.516,"timeframes":{"1m":{"touch":null,"r2":{"price":162.745,"dist":22.9,"touches":1,"rank":1,"conf":6},"r1":{"price":162.613,"dist":9.7,"touches":1,"rank":1,"conf":6},"s1":{"price":162.446,"dist":7,"touches":65,"rank":3,"conf":6},"s2":null},"5m":{"touch":null,"r2":{"price":162.745,"dist":22.9,"touches":1,"rank":1,"conf":6},"r1":{"price":162.613,"dist":9.7,"touches":1,"rank":1,"conf":6},"s1":{"price":162.421,"dist":9.5,"touches":90,"rank":3,"conf":6},"s2":null},"15m":{"touch":null,"r2":null,"r1":{"price":162.745,"dist":22.9,"touches":1,"rank":1,"conf":6},"s1":{"price":162.424,"dist":9.3,"touches":36,"rank":3,"conf":6},"s2":null},"1h":{"touch":null,"r2":null,"r1":{"price":162.745,"dist":22.9,"touches":1,"rank":1,"conf":6},"s1":{"price":162.391,"dist":12.5,"touches":23,"rank":3,"conf":6},"s2":{"price":162.016,"dist":50.1,"touches":2,"rank":1,"conf":2}},"4h":{"touch":null,"r2":null,"r1":{"price":162.779,"dist":26.2,"touches":2,"rank":1,"conf":6},"s1":{"price":162.386,"dist":13,"touches":9,"rank":3,"conf":6},"s2":{"price":161.683,"dist":83.3,"touches":7,"rank":3,"conf":1}},"1d":{"touch":null,"r2":{"price":162.779,"dist":26.2,"touches":2,"rank":2,"conf":6},"r1":{"price":162.548,"dist":3.2,"touches":1,"rank":1,"conf":6},"s1":{"price":162.007,"dist":50.9,"touches":1,"rank":1,"conf":2},"s2":{"price":161.813,"dist":70.3,"touches":1,"rank":1,"conf":2}}},"confluence":[{"price":162.48,"dist":3.6,"side":"S","tfs":["1m","5m","15m","1h","4h","1d"],"count":6},{"price":162.756,"dist":24,"side":"R","tfs":["1m","5m","15m","1h","4h","1d"],"count":6},{"price":161.933,"dist":58.3,"side":"S","tfs":["1h","1d"],"count":2},{"price":161.302,"dist":121.5,"side":"S","tfs":["4h","1d"],"count":2},{"price":160.635,"dist":188.1,"side":"S","tfs":["4h","1d"],"count":2}],"updated":"2026-07-19T23:05:19.058Z"}