{"symbol":"USD/JPY","price":162.709,"timeframes":{"1m":{"touch":{"price":162.733,"dist":2.4,"touches":48,"rank":3,"conf":4,"side":"R"},"r2":null,"r1":null,"s1":{"price":162.608,"dist":10.1,"touches":2,"rank":1,"conf":4},"s2":null},"5m":{"touch":null,"r2":null,"r1":{"price":162.845,"dist":13.6,"touches":1,"rank":1,"conf":4},"s1":{"price":162.64,"dist":6.9,"touches":32,"rank":3,"conf":4},"s2":{"price":162.292,"dist":41.7,"touches":17,"rank":1,"conf":3}},"15m":{"touch":null,"r2":null,"r1":{"price":162.807,"dist":9.8,"touches":2,"rank":2,"conf":4},"s1":{"price":162.608,"dist":10.1,"touches":10,"rank":3,"conf":4},"s2":{"price":162.252,"dist":45.7,"touches":12,"rank":3,"conf":3}},"1h":{"touch":null,"r2":null,"r1":null,"s1":{"price":162.673,"dist":3.6,"touches":1,"rank":1,"conf":4},"s2":{"price":162.534,"dist":17.5,"touches":1,"rank":1,"conf":4}},"4h":{"touch":null,"r2":null,"r1":null,"s1":{"price":162.03,"dist":67.9,"touches":3,"rank":2,"conf":2},"s2":{"price":161.779,"dist":92.9,"touches":4,"rank":2,"conf":3}},"1d":{"touch":null,"r2":null,"r1":null,"s1":{"price":162.007,"dist":70.2,"touches":1,"rank":1,"conf":2},"s2":{"price":161.813,"dist":89.6,"touches":1,"rank":1,"conf":3}}},"confluence":[{"price":162.681,"dist":2.8,"side":"S","tfs":["1m","5m","15m","1h"],"count":4},{"price":162.275,"dist":43.4,"side":"S","tfs":["5m","15m","1h"],"count":3},{"price":161.803,"dist":90.6,"side":"S","tfs":["15m","4h","1d"],"count":3},{"price":161.542,"dist":116.7,"side":"S","tfs":["15m","1h","4h"],"count":3},{"price":162.019,"dist":69,"side":"S","tfs":["4h","1d"],"count":2},{"price":161.04,"dist":166.9,"side":"S","tfs":["4h","1d"],"count":2}],"updated":"2026-07-01T06:00:38.296Z"}